spatialzoomer/__init__.py
spatialzoomer/multiscale_analysis/Identify_typical_scales.py
spatialzoomer/multiscale_analysis/Multiscale_analysis.py
spatialzoomer/multiscale_analysis/Preprocessing.py
spatialzoomer/multiscale_analysis/Simpson_Index.py
spatialzoomer/multiscale_analysis/Spectral_graph_filter_bank.py
spatialzoomer/multiscale_analysis/Two_step_Clustering.py
spatialzoomer/multiscale_analysis/Visualization.py
spatialzoomer/multiscale_analysis/__init__.py
spatialzoomer/subtype_detection/CFSFDP.py
spatialzoomer/subtype_detection/__init__.py
spatialzoomer/subtype_detection/spatial_neighborhood.py
spatialzoomer/subtype_detection/subtype_analysis_class.py
spatialzoomer/subtype_detection/utils.py
spatialzoomer/subtype_detection/visualization.py
spatialzoomer-0.1.1.dist-info/LICENSE
spatialzoomer-0.1.1.dist-info/METADATA
spatialzoomer-0.1.1.dist-info/WHEEL
spatialzoomer-0.1.1.dist-info/top_level.txt
spatialzoomer-0.1.1.dist-info/RECORD
