Metadata-Version: 2.1
Name: SpatialZoomer
Version: 0.1.1
Summary: Multi-scale feature analysis of spatial transcriptomics
Author-email: Xinqi Li <lxq19@mails.tsinghua.edu.cn>, Yuhan Fan <fyh22@mails.tsinghua.edu.cn>
License: MIT License
Classifier: Programming Language :: Python :: 3
Classifier: License :: OSI Approved :: MIT License
Classifier: Operating System :: OS Independent
Classifier: Intended Audience :: Science/Research
Classifier: Topic :: Scientific/Engineering :: Bio-Informatics
Requires-Python: >=3.8
License-File: LICENSE
Requires-Dist: numpy
Requires-Dist: matplotlib
Requires-Dist: scanpy
Requires-Dist: squidpy
Requires-Dist: seaborn
Requires-Dist: scipy
Requires-Dist: kneed
Requires-Dist: pandas
Requires-Dist: scikit-learn
Requires-Dist: pygsp
Requires-Dist: python-igraph
Requires-Dist: leidenalg
Requires-Dist: ipykernel
